nexus_bundler/__init__.py
nexus_bundler/bundler.py
nexus_bundler/nexus_instance.py
nexus_bundler/publishers/__init__.py
nexus_bundler/publishers/apt_publisher.py
nexus_bundler/publishers/base_publisher.py
nexus_bundler/publishers/docker_publisher.py
nexus_bundler/publishers/git_publisher.py
nexus_bundler/publishers/helm_publisher.py
nexus_bundler/publishers/maven_publisher.py
nexus_bundler/publishers/npm_publisher.py
nexus_bundler/publishers/nuget_publisher.py
nexus_bundler/publishers/py.typed
nexus_bundler/publishers/pypi_publisher.py
nexus_bundler/publishers/raw_publisher.py
nexus_bundler/publishers/yum_publisher.py
nexus_bundler/py.typed
hoppr_nexus_bundler-0.5.13.dist-info/LICENSE
hoppr_nexus_bundler-0.5.13.dist-info/METADATA
hoppr_nexus_bundler-0.5.13.dist-info/WHEEL
hoppr_nexus_bundler-0.5.13.dist-info/entry_points.txt
hoppr_nexus_bundler-0.5.13.dist-info/RECORD
