Metadata-Version: 2.3
Name: hoppr_nexus_bundler
Version: 0.5.13
Summary: Plug-in for Hoppr to bundle artifacts into a Nexus Repository
License: MIT
Keywords: hoppr,plugin,nexus
Author: LMCO Open Source
Author-email: open.source@lmco.com
Requires-Python: >=3.10,<4.0
Classifier: Development Status :: 2 - Pre-Alpha
Classifier: Intended Audience :: Information Technology
Classifier: License :: OSI Approved :: MIT License
Classifier: Programming Language :: Python :: 3
Classifier: Programming Language :: Python :: 3.10
Classifier: Programming Language :: Python :: 3.11
Classifier: Programming Language :: Python :: 3.12
Classifier: Programming Language :: Python :: 3.13
Classifier: Topic :: Communications :: File Sharing
Classifier: Topic :: Software Development :: Version Control
Classifier: Topic :: System :: Software Distribution
Requires-Dist: hoppr (==1.14.0)
Requires-Dist: semver (>=3.0.1,<4.0.0)
Project-URL: Homepage, https://hoppr.dev
Project-URL: Repository, https://gitlab.com/hoppr/plugins/hoppr-nexus-bundler
